sodarstest-0.0.2.dist-info/METADATA
sodarstest-0.0.2.dist-info/WHEEL
sodarstest/__init__.py
sodarstest/sodarstest.cpython-310-x86_64-linux-gnu.so
sodarstest-0.0.2.dist-info/RECORD
